pyserialnumbers-1.0.1.dist-info/licenses/LICENSE
serialnumbers/__init__.py
serialnumbers/_version.py
serialnumbers/common.py
serialnumbers/sn.py
pyserialnumbers-1.0.1.dist-info/METADATA
pyserialnumbers-1.0.1.dist-info/WHEEL
pyserialnumbers-1.0.1.dist-info/top_level.txt
pyserialnumbers-1.0.1.dist-info/RECORD
