Metadata-Version: 2.4
Name: PySerialNumbers
Version: 1.0.1
Summary: The PySerialNumbers library offers functionalities for manipulating serial numbers.
Home-page: https://github.com/dassym/PySerialNumbers
Author: Fabrice Voillat
Author-email: dev@dassym.com
Keywords: Dassym,motor,api,dapi
Classifier: Programming Language :: Python :: 3
Classifier: Operating System :: OS Independent
Requires-Python: >=3.4
License-File: LICENSE
Dynamic: author
Dynamic: author-email
Dynamic: classifier
Dynamic: description
Dynamic: description-content-type
Dynamic: home-page
Dynamic: keywords
Dynamic: license-file
Dynamic: requires-python
Dynamic: summary
